rkstiff/__init__.py
rkstiff/__version__.py
rkstiff/derivatives.py
rkstiff/etd.py
rkstiff/etd34.py
rkstiff/etd35.py
rkstiff/etd4.py
rkstiff/etd5.py
rkstiff/grids.py
rkstiff/if34.py
rkstiff/if4.py
rkstiff/if45dp.py
rkstiff/models.py
rkstiff/solver.py
rkstiff/solveras.py
rkstiff/solvercs.py
rkstiff/transforms.py
rkstiff/util/__init__.py
rkstiff/util/loghelper.py
rkstiff/util/solver_type.py
rkstiff-1.0.2.dist-info/licenses/LICENSE
rkstiff-1.0.2.dist-info/METADATA
rkstiff-1.0.2.dist-info/WHEEL
rkstiff-1.0.2.dist-info/top_level.txt
rkstiff-1.0.2.dist-info/RECORD
