Metadata-Version: 2.4
Name: rkstiff
Version: 1.0.2
Summary: 'Runge-Kutta adaptive-step and constant-step solvers for nonlinear PDEs'
Author-email: Patrick Whalen <whalenpt@gmail.com>
License: MIT License
Project-URL: homepage, https://github.com/whalenpt/rkstiff
Project-URL: documentation, https://github.com/whalenpt/rkstiff
Project-URL: repository, https://github.com/whalenpt/rkstiff
Project-URL: Bug Tracker, https://github.com/whalenpt/rkstiff/issues
Keywords: ETD,Runge-Kutta,Nonlinear PDEs
Classifier: Development Status :: 4 - Beta
Classifier: Intended Audience :: Science/Research
Classifier: Topic :: Scientific/Engineering :: Mathematics
Classifier: Programming Language :: Python :: 3
Classifier: Programming Language :: Python :: 3.9
Classifier: Programming Language :: Python :: 3.10
Classifier: Programming Language :: Python :: 3.11
Classifier: Programming Language :: Python :: 3.12
Classifier: Programming Language :: Python :: 3.13
Classifier: License :: OSI Approved :: MIT License
Classifier: Operating System :: OS Independent
Requires-Python: >=3.9
License-File: LICENSE
Requires-Dist: numpy>=1.21.0
Requires-Dist: scipy>=1.7.0
Provides-Extra: demo
Requires-Dist: matplotlib>=3.8.0; extra == "demo"
Requires-Dist: jupyter>=1.0.0; extra == "demo"
Provides-Extra: dev
Requires-Dist: black>=22.0.0; extra == "dev"
Requires-Dist: flake8>=5.0.0; extra == "dev"
Requires-Dist: mccabe>=0.7.0; extra == "dev"
Requires-Dist: mypy>=0.990; extra == "dev"
Requires-Dist: pylint>=2.15.0; extra == "dev"
Requires-Dist: twine>=4.0.0; extra == "dev"
Requires-Dist: pre-commit>=2.20.0; extra == "dev"
Provides-Extra: test
Requires-Dist: pytest>=7.0.0; extra == "test"
Requires-Dist: pytest-cov>=3.0.0; extra == "test"
Requires-Dist: pytest-xdist>=2.5.0; extra == "test"
Requires-Dist: tox>=3.27.0; extra == "test"
Provides-Extra: docs
Requires-Dist: sphinx>=7.0.0; extra == "docs"
Requires-Dist: sphinx-autodoc-typehints>=2.0.0; extra == "docs"
Requires-Dist: sphinx-rtd-theme>=1.3.0; extra == "docs"
Requires-Dist: myst-parser>=2.0.0; extra == "docs"
Requires-Dist: linkify-it-py>=2.0.0; extra == "docs"
Provides-Extra: all
Requires-Dist: rkstiff[demo,dev,docs,test]; extra == "all"
Dynamic: license-file
